python_ini/__init__.py
python_ini/__main__.py
python_ini/ast_callbacks.py
python_ini/grammar.py
python_ini/help.py
python_ini/ini_file.py
python_ini/ini_writer.py
python_ini/parser_callbacks.py
python_ini-1.1.0.dist-info/LICENSE
python_ini-1.1.0.dist-info/METADATA
python_ini-1.1.0.dist-info/WHEEL
python_ini-1.1.0.dist-info/entry_points.txt
python_ini-1.1.0.dist-info/top_level.txt
python_ini-1.1.0.dist-info/RECORD
