Metadata-Version: 2.1
Name: python-ini
Version: 1.1.0
Summary: A simple to use yet very flexible INI file parser and writer.
Author-email: Lowell Thomas <ldt@sabnf.com>
License: BSD 2-Clause License
Project-URL: Homepage, https://github.com/ldthomas/python-ini
Project-URL: Bug Tracker, https://github.com/ldthomas/python-ini/issues
Classifier: Programming Language :: Python :: 3
Classifier: License :: OSI Approved :: BSD License
Classifier: Operating System :: OS Independent
Requires-Python: >=3.7
License-File: LICENSE
Requires-Dist: apg-py
